brainfuck_fuck/__init__.py
brainfuck_fuck/__main__.py
brainfuck_fuck/getch.py
brainfuck_fuck-2020.5.11.dist-info/LICENSE
brainfuck_fuck-2020.5.11.dist-info/METADATA
brainfuck_fuck-2020.5.11.dist-info/WHEEL
brainfuck_fuck-2020.5.11.dist-info/entry_points.txt
brainfuck_fuck-2020.5.11.dist-info/top_level.txt
brainfuck_fuck-2020.5.11.dist-info/RECORD
