Metadata-Version: 1.1
Name: brainfuck-fuck
Version: 2020.5.11
Summary: Just a nice little brainfuck interpreter in Python.
Home-page: https://github.com/Kenny2github/brainfuck-fuck
Author: Ken Hilton
Author-email: kenny2minecraft@gmail.com
License: MIT
Keywords: brainfuck interpreter brainfuck-fuck
Platform: UNKNOWN
Classifier: Development Status :: 3 - Alpha
Classifier: License :: OSI Approved :: MIT License
Classifier: Programming Language :: Python :: 3.6
Classifier: Topic :: Software Development :: Interpreters
